Workbook

Sheet DASHBOARD-CFO
BG200: Índices de Liquidez
BG204: =DADOS!B1/DADOS!B4 -> 0.2 | BM204: =(DADOS!B1-DADOS!B3)/DADOS!B4 -> 0.1 | BS204: 600.13 | BY204: 583.41
BG208: Liquidez Corrente | BM208: Liquidez Seca | BS208: Liquidez Imediata | BY208: Liquidez Geral
BG233: Índices de Endividamento
BG237: =(DADOS!B4+DADOS!B5)/DADOS!B6 -> 5.6666667 | BM237: =DADOS!B4/(DADOS!B4+DADOS!B5) -> 0.98039216 | BS237: =DADOS!B2/DADOS!B6 -> 5.5555556
BG241: Participação de Capital de Terceiros | BM241: Composição do Endividamento | BS241: Imobilização do Patrimônio Líquido
BG284: Evolução Temporal
BG288: 496000 | BM288: 489632 | BS288: 6368
BG292: Receita Líquida | BM292: CPV | BS292: Lucro Bruto
BG319: Análise de Receita por Usuários (RPU)
BG323: =DADOS!B9/DADOS!D9 -> 20 | BP323: =DADOS!B10/DADOS!C10 -> 4.2826552 | BY323: =DADOS!B11/DADOS!C11 -> 242.42424
BG327: RPU Mensal Geral | BP327: RPU Usuário Gratuitos | BY327: RPU Usuários Pagantes
BK330: 81.18 | BU330: 422.1
BK334: LTV Usuários Gratuitos | BU334: LTV Usuários Pagantes
BI337: Janeiro | BJ337: Taxa | BK337: Fevereiro | BL337: Taxa | BM337: Março | BN337: Taxa | BO337: Abril | BP337: Taxa | BQ337: Maio | BR337: Taxa | BS337: Junho | BT337: Taxa | BU337: Julho | BV337: Taxa | BW337: Agosto | BX337: Taxa | BY337: Setembro | BZ337: Taxa | CA337: Outubro | CB337: Taxa | CC337: Novembro | CD337: Taxa | CE337: Dezembro | CF337: Taxa
BG338: RPU Mensal Geral | BI338: 5 | BJ338: 0.02 | BK338: 3 | BL338: =(1-(BK338/BI338))*(-1) -> -0.4 | BM338: 6 | BN338: =(1-(BM338/BK338))*(-1) -> 1 | BO338: 6.1 | BP338: =(1-(BO338/BM338))*(-1) -> 0.016666667 | BQ338: 7 | BR338: =(1-(BQ338/BO338))*(-1) -> 0.14754098 | BS338: 8 | BT338: =(1-(BS338/BQ338))*(-1) -> 0.14285714 | BU338: 6 | BV338: =(1-(BU338/BS338))*(-1) -> -0.25 | BW338: 4 | BX338: =(1-(BW338/BU338))*(-1) -> -0.33333333 | BY338: 10 | BZ338: =(1-(BY338/BW338))*(-1) -> 1.5 | CB338: =(1-(CA338/BY338))*(-1) -> -1 | CD338: =(1-(CC338/CA338))*(-1) -> #DIV/0! | CF338: =(1-(CE338/CC338))*(-1) -> #DIV/0!
BG339: RPU Usuário Gratuitos | BI339: 1.2 | BJ339: 0.02 | BK339: 0.8 | BL339: =(1-(BK339/BI339))*(-1) -> -0.33333333 | BM339: 2.2 | BN339: =(1-(BM339/BK339))*(-1) -> 1.75 | BO339: 2.3 | BP339: =(1-(BO339/BM339))*(-1) -> 0.045454545 | BQ339: 3 | BR339: =(1-(BQ339/BO339))*(-1) -> 0.30434783 | BS339: 4 | BT339: =(1-(BS339/BQ339))*(-1) -> 0.33333333 | BU339: 2 | BV339: =(1-(BU339/BS339))*(-1) -> -0.5 | BW339: 3 | BX339: =(1-(BW339/BU339))*(-1) -> 0.5 | BY339: 20 | BZ339: =(1-(BY339/BW339))*(-1) -> 5.6666667 | CB339: =(1-(CA339/BY339))*(-1) -> -1 | CD339: =(1-(CC339/CA339))*(-1) -> #DIV/0! | CF339: =(1-(CE339/CC339))*(-1) -> #DIV/0!
BG340: RPU Usuários Pagantes | BI340: 80.42 | BJ340: 0.01 | BK340: 70.41 | BL340: =(1-(BK340/BI340))*(-1) -> -0.12447152 | BM340: 50.41 | BN340: =(1-(BM340/BK340))*(-1) -> -0.28405056 | BO340: 50.42 | BP340: =(1-(BO340/BM340))*(-1) -> 0.00019837334 | BQ340: 51 | BR340: =(1-(BQ340/BO340))*(-1) -> 0.011503372 | BS340: 52 | BT340: =(1-(BS340/BQ340))*(-1) -> 0.019607843 | BU340: 53 | BV340: =(1-(BU340/BS340))*(-1) -> 0.019230769 | BW340: 58 | BX340: =(1-(BW340/BU340))*(-1) -> 0.094339623 | BY340: 30 | BZ340: =(1-(BY340/BW340))*(-1) -> -0.48275862 | CB340: =(1-(CA340/BY340))*(-1) -> -1 | CD340: =(1-(CC340/CA340))*(-1) -> #DIV/0! | CF340: =(1-(CE340/CC340))*(-1) -> #DIV/0!
BG341: LTV Usuários Gratuitos | BI341: 24.4 | BJ341: 0.03 | BK341: 26.4 | BL341: =(1-(BK341/BI341))*(-1) -> 0.081967213 | BM341: 24.4 | BN341: =(1-(BM341/BK341))*(-1) -> -0.075757576 | BO341: 24.9 | BP341: =(1-(BO341/BM341))*(-1) -> 0.020491803 | BQ341: 26 | BR341: =(1-(BQ341/BO341))*(-1) -> 0.044176707 | BS341: 27 | BT341: =(1-(BS341/BQ341))*(-1) -> 0.038461538 | BU341: 28 | BV341: =(1-(BU341/BS341))*(-1) -> 0.037037037 | BW341: 26 | BX341: =(1-(BW341/BU341))*(-1) -> -0.071428571 | BY341: 40 | BZ341: =(1-(BY341/BW341))*(-1) -> 0.53846154 | CB341: =(1-(CA341/BY341))*(-1) -> -1 | CD341: =(1-(CC341/CA341))*(-1) -> #DIV/0! | CF341: =(1-(CE341/CC341))*(-1) -> #DIV/0!
BG342: LTV Usuários Pagantes | BI342: 40.21 | BJ342: 0.04 | BK342: 40.29 | BL342: =(1-(BK342/BI342))*(-1) -> 0.0019895548 | BM342: 4.2 | BN342: =(1-(BM342/BK342))*(-1) -> -0.89575577 | BO342: 4.9 | BP342: =(1-(BO342/BM342))*(-1) -> 0.16666667 | BQ342: 6 | BR342: =(1-(BQ342/BO342))*(-1) -> 0.2244898 | BS342: 8 | BT342: =(1-(BS342/BQ342))*(-1) -> 0.33333333 | BU342: 10 | BV342: =(1-(BU342/BS342))*(-1) -> 0.25 | BW342: 9 | BX342: =(1-(BW342/BU342))*(-1) -> -0.1 | BY342: 50 | BZ342: =(1-(BY342/BW342))*(-1) -> 4.5555556 | CB342: =(1-(CA342/BY342))*(-1) -> -1 | CD342: =(1-(CC342/CA342))*(-1) -> #DIV/0! | CF342: =(1-(CE342/CC342))*(-1) -> #DIV/0!

Sheet Planilha1
A1: Cashbark | B1: Janeiro | C1: Fevereiro | D1: Março | E1: Abril | F1: Maio | G1: Junho | H1: Julho | I1: Agosto | J1: Setembro | K1: Outubro | L1: Novembro | M1: Dezembro
A2: Receita Total | B2: 850000 | C2: 935000 | D2: 800000 | E2: 1000000 | F2: 235000 | G2: 600000 | H2: 799000 | I2: 589006 | J2: 496000 | K2: 1232000 | L2: 988600 | M2: 888888
A3: Volume de transacoes | B3: 100 | C3: 50 | D3: 60 | E3: 80 | F3: 200 | G3: 260 | H3: 420 | I3: 480 | J3: 557 | K3: 600 | L3: 700 | M3: 800
A4: Ticket Medio | B4: =B2/B3 -> 8500 | C4: =C2/C3 -> 18700 | D4: =D2/D3 -> 13333.333 | E4: =E2/E3 -> 12500 | F4: =F2/F3 -> 1175 | G4: =G2/G3 -> 2307.6923 | H4: =H2/H3 -> 1902.381 | I4: =I2/I3 -> 1227.0958 | ... M4: =M2/M3 -> 1111.11
A6: Produto | B6: Janeiro | C6: Fevereiro | D6: Março | E6: Abril | F6: Maio | G6: Junho | H6: Julho | I6: Agosto | J6: Setembro | K6: Outubro | L6: Novembro | M6: Dezembro
A7: Receita Total | B7: 100000 | C7: 50000 | D7: 100000 | E7: 600000 | F7: 543000 | G7: 45000 | H7: 102000 | I7: 150326 | J7: 489632 | K7: 400000 | L7: 450000 | M7: 500000
A8: Volume de transacoes | B8: 100 | C8: 50 | D8: 60 | E8: 80 | F8: 200 | G8: 260 | H8: 420 | I8: 480 | J8: 557 | K8: 600 | L8: 700 | M8: 800
A9: Ticket Medio | B9: =B7/B8 -> 1000 | C9: =C7/C8 -> 1000 | D9: =D7/D8 -> 1666.6667 | E9: =E7/E8 -> 7500 | F9: =F7/F8 -> 2715 | G9: =G7/G8 -> 173.07692 | H9: =H7/H8 -> 242.85714 | I9: =I7/I8 -> 313.17917 | ... M9: =M7/M8 -> 625
A11: Deconto | B11: Janeiro | C11: Fevereiro | D11: Março | E11: Abril | F11: Maio | G11: Junho | H11: Julho | I11: Agosto | J11: Setembro | K11: Outubro | L11: Novembro | M11: Dezembro
A12: Receita Total | B12: 242343 | C12: 43243 | D12: 234432 | E12: 234432 | F12: 424223 | G12: 23532 | H12: 233243 | I12: 342234 | J12: 423234 | K12: 243432 | L12: 533534 | M12: 344334
A13: Volume de transacoes | B13: 100 | C13: 50 | D13: 60 | E13: 80 | F13: 200 | G13: 260 | H13: 420 | I13: 480 | J13: 557 | K13: 600 | L13: 700 | M13: 800
A14: Ticket Medio | B14: =B12/B13 -> 2423.43 | C14: =C12/C13 -> 864.86 | D14: =D12/D13 -> 3907.2 | E14: =E12/E13 -> 2930.4 | F14: =F12/F13 -> 2121.115 | G14: =G12/G13 -> 90.507692 | H14: =H12/H13 -> 555.34048 | I14: =I12/I13 -> 712.9875 | ... M14: =M12/M13 -> 430.4175
B18: Cashbark | C18: Produto | D18: Desconto | G18: Soma dos Tipos do Cupom
A19: Repasses | B19: 5009990 | C19: 600796 | D19: 420212 | F19: Receita | G19: =SUM(B2:M2)+SUM(B7:M7)+SUM(B12:M12) -> 16265668
A20: Margem Operacional | B20: =B19/SUM(B2:M2) -> 0.53221365 | C20: =C19/SUM(B7:M7) -> 0.17019919 | D20: =D19/SUM(B12:M12) -> 0.12648545 | F20: Repasses | G20: =SUM(B19:D19) -> 6030998
B21: =1-B20 -> 0.46778635 | C21: =1-C20 -> 0.82980081 | D21: =1-D20 -> 0.87351455
A22: Receita Liquida | B22: =SUM(B2:M2)-B19 -> 4403504 | C22: =SUM(B7:M7)-C19 -> 2929162 | D22: =SUM(B12:M12)-D19 -> 2902004
B23: Manha | C23: Tarde | D23: Noite
A24: Participacao do Usuario | B24: 13123 | C24: 14312 | D24: 24124
B25: Seg | C25: Ter | D25: Qua | E25: Qui | F25: Sex | G25: Sab | H25: Dom
A26: Participacao do Usuario | B26: 122213 | C26: 122132 | D26: 241424 | E26: 121312 | F26: 341214 | G26: 123132 | H26: 132132
A28: Ticket Medio Diária | B28: Seg | C28: Ter | D28: Qua | E28: Qui | F28: Sex | G28: Sab | H28: Dom
A29: Receita Total | B29: 850000 | C29: 935000 | D29: 800000 | E29: 1000000 | F29: 235000 | G29: 600000 | H29: 799000
A30: Transacoes | B30: 100 | C30: 50 | D30: 60 | E30: 80 | F30: 200 | G30: 260 | H30: 420
A31: Ticket Medio | B31: =B29/B30 -> 8500 | C31: =C29/C30 -> 18700 | D31: =D29/D30 -> 13333.333 | E31: =E29/E30 -> 12500 | F31: =F29/F30 -> 1175 | G31: =G29/G30 -> 2307.6923 | H31: =H29/H30 -> 1902.381
B32: A | C32: B | D32: C | E32: D | F32: E
A33: Categoria | B33: 123322 | C33: 123132 | D33: 234432 | E33: 234324 | F33: 234432
A34: Receita Total | B34: 132312312 | C34: 132321321 | D34: 132132321 | E34: 312312321 | F34: 312312321

Sheet DADOS
A1: Ativo Circulante | B1: 1000000 | F1: Item | G1: Janeiro | H1: Fevereiro | I1: Março | J1: Abril | K1: Maio | L1: Junho | M1: Julho | N1: Agosto | O1: Setembro | P1: Outubro | Q1: Novembro | R1: Dezembro
A2: Ativo Não Circulante | B2: 5000000 | F2: Receita Líquida | G2: 850000 | H2: 935000 | I2: 800000 | J2: 1000000 | K2: 235000 | L2: 600000 | M2: 799000 | N2: 589006 | O2: 496000 | P2: 1232000 | Q2: 988600 | R2: 888888
A3: Estoques | B3: 500000 | F3: CPV | G3: 100000 | H3: 50000 | I3: 100000 | J3: 600000 | K3: 543000 | L3: 45000 | M3: 102000 | N3: 150326 | O3: 489632 | P3: 400000 | Q3: 450000 | R3: 500000
A4: Passivo Circulante | B4: 5000000 | F4: Lucro Bruto | G4: =G2-G3 -> 750000 | H4: =H2-H3 -> 885000 | I4: =I2-I3 -> 700000 | J4: =J2-J3 -> 400000 | K4: =K2-K3 -> -308000 | L4: =L2-L3 -> 555000 | M4: =M2-M3 -> 697000 | N4: =N2-N3 -> 438680 | ... R4: =R2-R3 -> 388888
A5: Passivo Não Circulante | B5: 100000
A6: Patrimônio Líquido | B6: =SUM(B1:B2)-SUM(B4:B5) -> 900000 | F6: Item | G6: Janeiro | H6: Fevereiro | I6: Março | J6: Abril | K6: Maio | L6: Junho | M6: Julho | N6: Agosto | O6: Setembro | P6: Outubro | Q6: Novembro | R6: Dezembro
F7: PCT | G7: 100 | H7: 50 | I7: 60 | J7: 80 | K7: 200 | L7: 260 | M7: 420 | N7: 480 | O7: 557 | P7: 600 | Q7: 700 | R7: 800
F8: CE | G8: 20 | H8: 10 | I8: 20 | J8: 40 | K8: 70 | L8: 90 | M8: 120 | N8: 130 | O8: 98 | P8: 120 | Q8: 120 | R8: 150
A9: Receita Total Mensal | B9: =B10+B11 -> 1000000 | C9: Qtde. de Usuário | D9: 50000 | F9: IPL | G9: 100 | H9: 120 | I9: 90 | J9: 60 | K9: 160 | L9: 250 | M9: 380 | N9: 470 | O9: 556 | P9: 600 | Q9: 600 | R9: 700
A10: Receita Total Usuários G | B10: 200000 | C10: 46700
A11: RPU Usuários Pagantes | B11: 800000 | C11: 3300 | H11: Janeiro | J11: Fevereiro | L11: Março | N11: Abril | P11: Maio | R11: Junho | T11: Julho | V11: Agosto | X11: Setembro | Z11: Outubro | AA11: Taxa
F12: RPU Mensal Geral | H12: 5 | J12: 3 | L12: 6 | N12: 6.1 | P12: 7 | R12: 8 | T12: 6 | V12: 4 | X12: 10 | AA12: =(1-(Z12/X12))*(-1) -> -1
F13: RPU Usuário Gratuitos | H13: 1.2 | J13: 0.8 | L13: 2.2 | N13: 2.3 | P13: 3 | R13: 4 | T13: 2 | V13: 3 | X13: 20 | AA13: =(1-(Z13/X13))*(-1) -> -1
F14: RPU Usuários Pagantes | H14: 80.42 | J14: 70.41 | L14: 50.41 | N14: 50.42 | P14: 51 | R14: 52 | T14: 53 | V14: 58 | X14: 30 | AA14: =(1-(Z14/X14))*(-1) -> -1
F15: LTV Usuários Gratuitos | H15: 24.4 | J15: 26.4 | L15: 24.4 | N15: 24.9 | P15: 26 | R15: 27 | T15: 28 | V15: 26 | X15: 40 | AA15: =(1-(Z15/X15))*(-1) -> -1
F16: LTV Usuários Pagantes | H16: 40.21 | J16: 40.29 | L16: 4.2 | N16: 4.9 | P16: 6 | R16: 8 | T16: 10 | V16: 9 | X16: 50 | AA16: =(1-(Z16/X16))*(-1) -> -1
H18: Janeiro | I18: Fevereiro | J18: Março | K18: Abril | L18: Maio | M18: Junho | N18: Julho | O18: Agosto | P18: Setembro | Q18: Outubro
F19: RPU Mensal Geral | H19: 0.02 | I19: -0.4 | J19: =(1-(J12/H12))*(-1) -> -0.4 | K19: =(1-(L12/J12))*(-1) -> 1 | L19: =(1-(N12/L12))*(-1) -> 0.016666667 | M19: =(1-(P12/N12))*(-1) -> 0.14754098 | N19: =(1-(R12/P12))*(-1) -> 0.14285714 | O19: =(1-(T12/R12))*(-1) -> -0.25 | P19: =(1-(V12/T12))*(-1) -> -0.33333333 | Q19: =(1-(X12/V12))*(-1) -> 1.5
F20: RPU Usuário Gratuitos | H20: 0.02 | I20: -0.33333333 | J20: =(1-(J13/H13))*(-1) -> -0.33333333 | K20: =(1-(L13/J13))*(-1) -> 1.75 | L20: =(1-(N13/L13))*(-1) -> 0.045454545 | M20: =(1-(P13/N13))*(-1) -> 0.30434783 | N20: =(1-(R13/P13))*(-1) -> 0.33333333 | O20: =(1-(T13/R13))*(-1) -> -0.5 | P20: =(1-(V13/T13))*(-1) -> 0.5 | Q20: =(1-(X13/V13))*(-1) -> 5.6666667
F21: RPU Usuários Pagantes | H21: 0.01 | I21: -0.12447152 | J21: =(1-(J14/H14))*(-1) -> -0.12447152 | K21: =(1-(L14/J14))*(-1) -> -0.28405056 | L21: =(1-(N14/L14))*(-1) -> 0.00019837334 | M21: =(1-(P14/N14))*(-1) -> 0.011503372 | N21: =(1-(R14/P14))*(-1) -> 0.019607843 | O21: =(1-(T14/R14))*(-1) -> 0.019230769 | P21: =(1-(V14/T14))*(-1) -> 0.094339623 | Q21: =(1-(X14/V14))*(-1) -> -0.48275862
F22: LTV Usuários Gratuitos | H22: 0.03 | I22: 0.081967213 | J22: =(1-(J15/H15))*(-1) -> 0.081967213 | K22: =(1-(L15/J15))*(-1) -> -0.075757576 | L22: =(1-(N15/L15))*(-1) -> 0.020491803 | M22: =(1-(P15/N15))*(-1) -> 0.044176707 | N22: =(1-(R15/P15))*(-1) -> 0.038461538 | O22: =(1-(T15/R15))*(-1) -> 0.037037037 | P22: =(1-(V15/T15))*(-1) -> -0.071428571 | Q22: =(1-(X15/V15))*(-1) -> 0.53846154
F23: LTV Usuários Pagantes | H23: 0.04 | I23: 0.0019895548 | J23: =(1-(J16/H16))*(-1) -> 0.0019895548 | K23: =(1-(L16/J16))*(-1) -> -0.89575577 | L23: =(1-(N16/L16))*(-1) -> 0.16666667 | M23: =(1-(P16/N16))*(-1) -> 0.2244898 | N23: =(1-(R16/P16))*(-1) -> 0.33333333 | O23: =(1-(T16/R16))*(-1) -> 0.25 | P23: =(1-(V16/T16))*(-1) -> -0.1 | Q23: =(1-(X16/V16))*(-1) -> 4.5555556
