Workbook

Sheet DASHBOARD-CFO
B2: Índices de Liquidez
B6: =DADOS!B1/DADOS!B4 -> 0.2 | H6: =(DADOS!B1-DADOS!B3)/DADOS!B4 -> 0.1 | N6: 600.13 | T6: 600.13
B10: Liquidez Corrente | H10: Liquidez Seca | N10: Liquidez Imediata | T10: Liquidez Geral
B35: Índices de Endividamento
B39: =(DADOS!B4+DADOS!B5)/DADOS!B6 -> 5.6666667 | H39: =DADOS!B4/(DADOS!B4+DADOS!B5) -> 0.98039216 | N39: =DADOS!B2/DADOS!B6 -> 5.5555556
B43: Participação de Capital de Terceiros | H43: Composição do Endividamento | N43: Imobilização do Patrimônio Líquido
B86: Evolução Temporal
B90: 496000 | H90: 489632 | N90: 6368
B94: Receita Líquida | H94: CPV | N94: Lucro Bruto
B121: Análise de Receita por Usuários (RPU)
B125: =DADOS!B9/DADOS!D9 -> 20 | K125: =DADOS!B10/DADOS!C10 -> 4.2826552 | T125: =DADOS!B11/DADOS!C11 -> 242.42424
B129: RPU Mensal Geral | K129: RPU Usuário Gratuitos | T129: RPU Usuários Pagantes
F132: 81.18 | P132: 422.1
F136: LTV Usuários Gratuitos | P136: LTV Usuários Pagantes
D139: Janeiro | E139: Taxa | F139: Fevereiro | G139: Taxa | H139: Março | I139: Taxa | J139: Abril | K139: Taxa | L139: Maio | M139: Taxa | N139: Junho | O139: Taxa | P139: Julho | Q139: Taxa | R139: Agosto | S139: Taxa | T139: Setembro | U139: Taxa | V139: Outubro | W139: Taxa | X139: Novembro | Y139: Taxa | Z139: Dezembro | AA139: Taxa
B140: RPU Mensal Geral | D140: 5 | E140: 0.02 | F140: 3 | G140: =(1-(F140/D140))*(-1) -> -0.4 | H140: 6 | I140: =(1-(H140/F140))*(-1) -> 1 | J140: 6.1 | K140: =(1-(J140/H140))*(-1) -> 0.016666667 | L140: 7 | M140: =(1-(L140/J140))*(-1) -> 0.14754098 | N140: 8 | O140: =(1-(N140/L140))*(-1) -> 0.14285714 | P140: 6 | Q140: =(1-(P140/N140))*(-1) -> -0.25 | R140: 4 | S140: =(1-(R140/P140))*(-1) -> -0.33333333 | T140: 10 | U140: =(1-(T140/R140))*(-1) -> 1.5 | W140: =(1-(V140/T140))*(-1) -> -1 | Y140: =(1-(X140/V140))*(-1) -> #DIV/0! | AA140: =(1-(Z140/X140))*(-1) -> #DIV/0!
B141: RPU Usuário Gratuitos | D141: 1.2 | E141: 0.02 | F141: 0.8 | G141: =(1-(F141/D141))*(-1) -> -0.33333333 | H141: 2.2 | I141: =(1-(H141/F141))*(-1) -> 1.75 | J141: 2.3 | K141: =(1-(J141/H141))*(-1) -> 0.045454545 | L141: 3 | M141: =(1-(L141/J141))*(-1) -> 0.30434783 | N141: 4 | O141: =(1-(N141/L141))*(-1) -> 0.33333333 | P141: 2 | Q141: =(1-(P141/N141))*(-1) -> -0.5 | R141: 3 | S141: =(1-(R141/P141))*(-1) -> 0.5 | T141: 20 | U141: =(1-(T141/R141))*(-1) -> 5.6666667 | W141: =(1-(V141/T141))*(-1) -> -1 | Y141: =(1-(X141/V141))*(-1) -> #DIV/0! | AA141: =(1-(Z141/X141))*(-1) -> #DIV/0!
B142: RPU Usuários Pagantes | D142: 80.42 | E142: 0.01 | F142: 70.41 | G142: =(1-(F142/D142))*(-1) -> -0.12447152 | H142: 50.41 | I142: =(1-(H142/F142))*(-1) -> -0.28405056 | J142: 50.42 | K142: =(1-(J142/H142))*(-1) -> 0.00019837334 | L142: 51 | M142: =(1-(L142/J142))*(-1) -> 0.011503372 | N142: 52 | O142: =(1-(N142/L142))*(-1) -> 0.019607843 | P142: 53 | Q142: =(1-(P142/N142))*(-1) -> 0.019230769 | R142: 58 | S142: =(1-(R142/P142))*(-1) -> 0.094339623 | T142: 30 | U142: =(1-(T142/R142))*(-1) -> -0.48275862 | W142: =(1-(V142/T142))*(-1) -> -1 | Y142: =(1-(X142/V142))*(-1) -> #DIV/0! | AA142: =(1-(Z142/X142))*(-1) -> #DIV/0!
B143: LTV Usuários Gratuitos | D143: 24.4 | E143: 0.03 | F143: 26.4 | G143: =(1-(F143/D143))*(-1) -> 0.081967213 | H143: 24.4 | I143: =(1-(H143/F143))*(-1) -> -0.075757576 | J143: 24.9 | K143: =(1-(J143/H143))*(-1) -> 0.020491803 | L143: 26 | M143: =(1-(L143/J143))*(-1) -> 0.044176707 | N143: 27 | O143: =(1-(N143/L143))*(-1) -> 0.038461538 | P143: 28 | Q143: =(1-(P143/N143))*(-1) -> 0.037037037 | R143: 26 | S143: =(1-(R143/P143))*(-1) -> -0.071428571 | T143: 40 | U143: =(1-(T143/R143))*(-1) -> 0.53846154 | W143: =(1-(V143/T143))*(-1) -> -1 | Y143: =(1-(X143/V143))*(-1) -> #DIV/0! | AA143: =(1-(Z143/X143))*(-1) -> #DIV/0!
B144: LTV Usuários Pagantes | D144: 40.21 | E144: 0.04 | F144: 40.29 | G144: =(1-(F144/D144))*(-1) -> 0.0019895548 | H144: 4.2 | I144: =(1-(H144/F144))*(-1) -> -0.89575577 | J144: 4.9 | K144: =(1-(J144/H144))*(-1) -> 0.16666667 | L144: 6 | M144: =(1-(L144/J144))*(-1) -> 0.2244898 | N144: 8 | O144: =(1-(N144/L144))*(-1) -> 0.33333333 | P144: 10 | Q144: =(1-(P144/N144))*(-1) -> 0.25 | R144: 9 | S144: =(1-(R144/P144))*(-1) -> -0.1 | T144: 50 | U144: =(1-(T144/R144))*(-1) -> 4.5555556 | W144: =(1-(V144/T144))*(-1) -> -1 | Y144: =(1-(X144/V144))*(-1) -> #DIV/0! | AA144: =(1-(Z144/X144))*(-1) -> #DIV/0!

Sheet DADOS
A1: Ativo Circulante | B1: 1000000 | F1: Item | G1: Janeiro | H1: Fevereiro | I1: Março | J1: Abril | K1: Maio | L1: Junho | M1: Julho | N1: Agosto | O1: Setembro | P1: Outubro | Q1: Novembro | R1: Dezembro
A2: Ativo Não Circulante | B2: 5000000 | F2: Receita Líquida | G2: 850000 | H2: 935000 | I2: 800000 | J2: 1000000 | K2: 235000 | L2: 600000 | M2: 799000 | N2: 589006 | O2: 496000 | P2: 1232000 | Q2: 988600 | R2: 888888
A3: Estoques | B3: 500000 | F3: CPV | G3: 100000 | H3: 50000 | I3: 100000 | J3: 600000 | K3: 543000 | L3: 45000 | M3: 102000 | N3: 150326 | O3: 489632 | P3: 400000 | Q3: 450000 | R3: 500000
A4: Passivo Circulante | B4: 5000000 | F4: Lucro Bruto | G4: =G2-G3 -> 750000 | H4: =H2-H3 -> 885000 | I4: =I2-I3 -> 700000 | J4: =J2-J3 -> 400000 | K4: =K2-K3 -> -308000 | L4: =L2-L3 -> 555000 | M4: =M2-M3 -> 697000 | N4: =N2-N3 -> 438680 | ... R4: =R2-R3 -> 388888
A5: Passivo Não Circulante | B5: 100000
A6: Patrimônio Líquido | B6: =SUM(B1:B2)-SUM(B4:B5) -> 900000 | F6: Item | G6: Janeiro | H6: Fevereiro | I6: Março | J6: Abril | K6: Maio | L6: Junho | M6: Julho | N6: Agosto | O6: Setembro | P6: Outubro | Q6: Novembro | R6: Dezembro
F7: PCT | G7: 100 | H7: 50 | I7: 60 | J7: 80 | K7: 200 | L7: 260 | M7: 420 | N7: 480 | O7: 557 | P7: 600 | Q7: 700 | R7: 800
F8: CE | G8: 20 | H8: 10 | I8: 20 | J8: 40 | K8: 70 | L8: 90 | M8: 120 | N8: 130 | O8: 98 | P8: 120 | Q8: 120 | R8: 150
A9: Receita Total Mensal | B9: =B10+B11 -> 1000000 | C9: Qtde. de Usuário | D9: 50000 | F9: IPL | G9: 100 | H9: 120 | I9: 90 | J9: 60 | K9: 160 | L9: 250 | M9: 380 | N9: 470 | O9: 556 | P9: 600 | Q9: 600 | R9: 700
A10: Receita Total Usuários G | B10: 200000 | C10: 46700
A11: RPU Usuários Pagantes | B11: 800000 | C11: 3300 | H11: Janeiro | J11: Fevereiro | L11: Março | N11: Abril | P11: Maio | R11: Junho | T11: Julho | V11: Agosto | X11: Setembro | Z11: Outubro | AA11: Taxa
F12: RPU Mensal Geral | H12: 5 | J12: 3 | L12: 6 | N12: 6.1 | P12: 7 | R12: 8 | T12: 6 | V12: 4 | X12: 10 | AA12: =(1-(Z12/X12))*(-1) -> -1
F13: RPU Usuário Gratuitos | H13: 1.2 | J13: 0.8 | L13: 2.2 | N13: 2.3 | P13: 3 | R13: 4 | T13: 2 | V13: 3 | X13: 20 | AA13: =(1-(Z13/X13))*(-1) -> -1
F14: RPU Usuários Pagantes | H14: 80.42 | J14: 70.41 | L14: 50.41 | N14: 50.42 | P14: 51 | R14: 52 | T14: 53 | V14: 58 | X14: 30 | AA14: =(1-(Z14/X14))*(-1) -> -1
F15: LTV Usuários Gratuitos | H15: 24.4 | J15: 26.4 | L15: 24.4 | N15: 24.9 | P15: 26 | R15: 27 | T15: 28 | V15: 26 | X15: 40 | AA15: =(1-(Z15/X15))*(-1) -> -1
F16: LTV Usuários Pagantes | H16: 40.21 | J16: 40.29 | L16: 4.2 | N16: 4.9 | P16: 6 | R16: 8 | T16: 10 | V16: 9 | X16: 50 | AA16: =(1-(Z16/X16))*(-1) -> -1
H18: Janeiro | I18: Fevereiro | J18: Março | K18: Abril | L18: Maio | M18: Junho | N18: Julho | O18: Agosto | P18: Setembro | Q18: Outubro
F19: RPU Mensal Geral | H19: 0.02 | I19: -0.4 | J19: =(1-(J12/H12))*(-1) -> -0.4 | K19: =(1-(L12/J12))*(-1) -> 1 | L19: =(1-(N12/L12))*(-1) -> 0.016666667 | M19: =(1-(P12/N12))*(-1) -> 0.14754098 | N19: =(1-(R12/P12))*(-1) -> 0.14285714 | O19: =(1-(T12/R12))*(-1) -> -0.25 | P19: =(1-(V12/T12))*(-1) -> -0.33333333 | Q19: =(1-(X12/V12))*(-1) -> 1.5
F20: RPU Usuário Gratuitos | H20: 0.02 | I20: -0.33333333 | J20: =(1-(J13/H13))*(-1) -> -0.33333333 | K20: =(1-(L13/J13))*(-1) -> 1.75 | L20: =(1-(N13/L13))*(-1) -> 0.045454545 | M20: =(1-(P13/N13))*(-1) -> 0.30434783 | N20: =(1-(R13/P13))*(-1) -> 0.33333333 | O20: =(1-(T13/R13))*(-1) -> -0.5 | P20: =(1-(V13/T13))*(-1) -> 0.5 | Q20: =(1-(X13/V13))*(-1) -> 5.6666667
F21: RPU Usuários Pagantes | H21: 0.01 | I21: -0.12447152 | J21: =(1-(J14/H14))*(-1) -> -0.12447152 | K21: =(1-(L14/J14))*(-1) -> -0.28405056 | L21: =(1-(N14/L14))*(-1) -> 0.00019837334 | M21: =(1-(P14/N14))*(-1) -> 0.011503372 | N21: =(1-(R14/P14))*(-1) -> 0.019607843 | O21: =(1-(T14/R14))*(-1) -> 0.019230769 | P21: =(1-(V14/T14))*(-1) -> 0.094339623 | Q21: =(1-(X14/V14))*(-1) -> -0.48275862
F22: LTV Usuários Gratuitos | H22: 0.03 | I22: 0.081967213 | J22: =(1-(J15/H15))*(-1) -> 0.081967213 | K22: =(1-(L15/J15))*(-1) -> -0.075757576 | L22: =(1-(N15/L15))*(-1) -> 0.020491803 | M22: =(1-(P15/N15))*(-1) -> 0.044176707 | N22: =(1-(R15/P15))*(-1) -> 0.038461538 | O22: =(1-(T15/R15))*(-1) -> 0.037037037 | P22: =(1-(V15/T15))*(-1) -> -0.071428571 | Q22: =(1-(X15/V15))*(-1) -> 0.53846154
F23: LTV Usuários Pagantes | H23: 0.04 | I23: 0.0019895548 | J23: =(1-(J16/H16))*(-1) -> 0.0019895548 | K23: =(1-(L16/J16))*(-1) -> -0.89575577 | L23: =(1-(N16/L16))*(-1) -> 0.16666667 | M23: =(1-(P16/N16))*(-1) -> 0.2244898 | N23: =(1-(R16/P16))*(-1) -> 0.33333333 | O23: =(1-(T16/R16))*(-1) -> 0.25 | P23: =(1-(V16/T16))*(-1) -> -0.1 | Q23: =(1-(X16/V16))*(-1) -> 4.5555556
